tippo/__init__.py
tippo/py.typed
tippo-4.1.1.dist-info/LICENSE
tippo-4.1.1.dist-info/METADATA
tippo-4.1.1.dist-info/WHEEL
tippo-4.1.1.dist-info/top_level.txt
tippo-4.1.1.dist-info/RECORD
